pyFunloader/__init__.py
pyFunloader/errors/__init__.py
pyFunloader/utils/__init__.py
pyFunloader-1.7.dist-info/METADATA
pyFunloader-1.7.dist-info/WHEEL
pyFunloader-1.7.dist-info/top_level.txt
pyFunloader-1.7.dist-info/RECORD
