Metadata-Version: 2.1
Name: pyFunloader
Version: 1.7
Author: Elfa Metesar
Requires-Dist: pycurl
